allauth_2fa/__init__.py
allauth_2fa/adapter.py
allauth_2fa/app_settings.py
allauth_2fa/forms.py
allauth_2fa/middleware.py
allauth_2fa/mixins.py
allauth_2fa/urls.py
allauth_2fa/utils.py
allauth_2fa/views.py
django_allauth_2fa-0.11.0.dist-info/METADATA
django_allauth_2fa-0.11.0.dist-info/WHEEL
django_allauth_2fa-0.11.0.dist-info/licenses/LICENSE
django_allauth_2fa-0.11.0.dist-info/RECORD
