Metadata-Version: 2.1
Name: django-allauth-2fa
Version: 0.11.0
Summary: Adds two factor authentication to django-allauth
Project-URL: Homepage, https://github.com/valohai/django-allauth-2fa
Author-email: Víðir Valberg Guðmundsson <valberg@orn.li>
License-Expression: Apache-2.0
License-File: LICENSE
Keywords: 2fa,allauth,auth,authentication,django,factor,otp,two
Classifier: Development Status :: 4 - Beta
Classifier: Environment :: Web Environment
Classifier: Framework :: Django
Classifier: Framework :: Django :: 3.2
Classifier: Framework :: Django :: 4.0
Classifier: Intended Audience :: Developers
Classifier: License :: OSI Approved :: Apache Software License
Classifier: Programming Language :: Python
Classifier: Programming Language :: Python :: 3.7
Classifier: Programming Language :: Python :: 3.8
Classifier: Programming Language :: Python :: 3.9
Classifier: Programming Language :: Python :: 3.10
Classifier: Programming Language :: Python :: 3.11
Classifier: Topic :: Internet
Classifier: Topic :: Software Development :: Libraries :: Python Modules
Requires-Python: >=3.7
Requires-Dist: django-allauth>=0.53.0
Requires-Dist: django-otp>=1.1.0
Requires-Dist: django>=3.2
Requires-Dist: qrcode>=5.3
